proctoring/__init__.py
proctoring/classes.TXT
proctoring/deploy.prototxt
proctoring/opencv_face_detector.pbtxt
proctoring/opencv_face_detector_uint8.pb
proctoring/proctoring.py
proctoring/res10_300x300_ssd_iter_140000.caffemodel
proctoring/pose_model/saved_model.pb
proctoring/pose_model/variables/variables.data-00000-of-00001
proctoring/pose_model/variables/variables.index
proctoring-0.0.1.dist-info/LICENSE
proctoring-0.0.1.dist-info/METADATA
proctoring-0.0.1.dist-info/WHEEL
proctoring-0.0.1.dist-info/top_level.txt
proctoring-0.0.1.dist-info/RECORD
