Metadata-Version: 2.1
Name: proctoring
Version: 0.0.1
Summary: Proctoring library
Home-page: UNKNOWN
Author: Narender Keswani
Author-email: narender.rk10@gmail.com
License: UNKNOWN
Keywords: proctoring,ai-proctoring,gaze-tracking
Platform: UNKNOWN
Classifier: Programming Language :: Python :: 3
Classifier: License :: OSI Approved :: MIT License
Classifier: Operating System :: OS Independent
Requires-Python: >=3.6
License-File: LICENSE
